PixeraPy/__init__.py
PixeraPy/api_functions.py
PixeraPy/pixera.py
pixerapy-0.461.1.dist-info/licenses/LICENSE.txt
pixerapy-0.461.1.dist-info/METADATA
pixerapy-0.461.1.dist-info/WHEEL
pixerapy-0.461.1.dist-info/top_level.txt
pixerapy-0.461.1.dist-info/RECORD
