Metadata-Version: 2.4
Name: PixeraPy
Version: 0.461.1
Summary: Python package for AVStumpfl, Pixera API
Home-page: https://github.com/Tedcharlesbrown/Pixera-TCB/tree/main/01-Custom/03-API
Author: Ted Charles Brown
Author-email: tedcharlesbrown@gmail.com
License: MIT
Classifier: Programming Language :: Python :: 3
Classifier: License :: OSI Approved :: MIT License
Classifier: Operating System :: OS Independent
Requires-Python: >=3.6
License-File: LICENSE.txt
Requires-Dist: requests
Dynamic: author
Dynamic: author-email
Dynamic: classifier
Dynamic: description
Dynamic: description-content-type
Dynamic: home-page
Dynamic: license
Dynamic: license-file
Dynamic: requires-dist
Dynamic: requires-python
Dynamic: summary
